Topsis/__init__.py
topsis_aviral_102303726-0.1.1.dist-info/METADATA
topsis_aviral_102303726-0.1.1.dist-info/WHEEL
topsis_aviral_102303726-0.1.1.dist-info/top_level.txt
topsis_aviral_102303726-0.1.1.dist-info/RECORD
