Metadata-Version: 2.1
Name: topsis-aviral-102303726
Version: 0.1.1
Summary: TOPSIS implementation in Python
